pod5Viewer/__init__.py
pod5Viewer/__main__.py
pod5Viewer/__version__.py
pod5Viewer/dataHandler.py
pod5Viewer/figureWindow.py
pod5Viewer/fileNavigator.py
pod5Viewer/icon.ico
pod5Viewer/idInputWindow.py
pod5Viewer/pod5Viewer.py
pod5Viewer/viewWindow.py
pod5Viewer/constants/__init__.py
pod5Viewer/constants/figureWindow_constants.py
pod5Viewer/constants/idInputWindow_constants.py
pod5Viewer/constants/pod5Viewer_constants.py
pod5Viewer/constants/viewWindow_constants.py
pod5Viewer-1.1.2.dist-info/LICENSE
pod5Viewer-1.1.2.dist-info/METADATA
pod5Viewer-1.1.2.dist-info/WHEEL
pod5Viewer-1.1.2.dist-info/entry_points.txt
pod5Viewer-1.1.2.dist-info/top_level.txt
pod5Viewer-1.1.2.dist-info/RECORD
