Metadata-Version: 2.1
Name: pod5Viewer
Version: 1.1.2
Summary: GUI for inspecting ONT pod5 files
Home-page: https://github.com/dietvin/pod5Viewer
Author: Vincent Dietrich
Author-email: dietricv@uni-mainz.de
License: LICENSE
Classifier: License :: OSI Approved :: GNU General Public License v3 (GPLv3)
Classifier: Programming Language :: Python :: 3
Classifier: Topic :: Scientific/Engineering :: Bio-Informatics
Classifier: Operating System :: OS Independent
Requires-Python: >3.9,<3.13
License-File: LICENSE
Requires-Dist: numpy==1.26.4
Requires-Dist: pod5==0.3.10
Requires-Dist: pyside6==6.5.2
Requires-Dist: matplotlib==3.9.2
